{"id":"3d33ee08-6a88-4cc5-9754-b7bcdbe19eb4","playerTags":[],"teamTags":["eb67ae5e-c4bf-46ca-bbbc-425cd34182ff"],"gameTags":["768c3770-3557-4acc-ae5c-a9312ee4db79"],"metadata":{"mod":"OVERPERFORMING","play":324,"type":3,"parent":"fbc0427d-de75-4a6d-ba7c-9b09156d3705","source":"HIGH_PRESSURE","subPlay":0},"created":"2021-03-17T08:28:01.261Z","season":13,"tournament":-1,"type":147,"day":40,"phase":4,"category":1,"description":"The pressure is off. The Moist Talkers are no longer Overperforming.","nuts":0}